neon_swarm/__init__.py
neon_swarm/agents.py
neon_swarm/main.py
neon_swarm/tools.py
neon_swarm-0.1.0.dist-info/METADATA
neon_swarm-0.1.0.dist-info/WHEEL
neon_swarm-0.1.0.dist-info/licenses/LICENSE
neon_swarm-0.1.0.dist-info/RECORD
