Metadata-Version: 2.3
Name: neon_swarm
Version: 0.1.0
Summary: Neon OpenAI Swarm Agent for interacting with Postgres and Neon databases
Project-URL: Homepage, https://github.com/raoufchebri/neon_swarm
Project-URL: Bug Tracker, https://github.com/raoufchebri/neon_swarm/issues
Author-email: Raouf Chebri <raouf.chebri@gmail.com>
License-File: LICENSE
Classifier: License :: OSI Approved :: MIT License
Classifier: Operating System :: OS Independent
Classifier: Programming Language :: Python :: 3
Requires-Python: >=3.10
Requires-Dist: psycopg2-binary
Requires-Dist: python-dotenv
Requires-Dist: requests
Provides-Extra: dev
Requires-Dist: pytest; extra == 'dev'
